setup.py
FireFoxDecrypt/__init__.py
FireFoxDecrypt/decryptor.py
FirefoxDecrypt.egg-info/PKG-INFO
FirefoxDecrypt.egg-info/SOURCES.txt
FirefoxDecrypt.egg-info/dependency_links.txt
FirefoxDecrypt.egg-info/requires.txt
FirefoxDecrypt.egg-info/top_level.txt