Metadata-Version: 1.2
Name: FirefoxDecrypt
Version: 0.2
Summary: Decrypt firefox logins in one line (FireFoxDecrypt.DecryptLogins('logins.json', 'key4.db', 'your_masterpassword_if_exists'))
Home-page: https://github.com/L1ghtM4n
Author: Lightman
Author-email: L1ghtM3n@protonmail.com
License: UNKNOWN
Platform: UNKNOWN
Classifier: Development Status :: 3 - Alpha
Classifier: Programming Language :: Python :: 3
Classifier: License :: OSI Approved :: MIT License
Classifier: Operating System :: OS Independent
Requires-Python: >=3.8
